xatch/__init__.py
xatch-0.1.1.dist-info/LICENSE
xatch-0.1.1.dist-info/WHEEL
xatch-0.1.1.dist-info/METADATA
xatch-0.1.1.dist-info/RECORD
